goat_wallets/multiversx/__init__.py
goat_wallets/multiversx/send_egld.py
goat_wallets/multiversx/types.py
goat_wallets/multiversx/wallet.py
goat_sdk_wallet_multiversx-0.1.0.dist-info/METADATA
goat_sdk_wallet_multiversx-0.1.0.dist-info/WHEEL
goat_sdk_wallet_multiversx-0.1.0.dist-info/RECORD
