Metadata-Version: 2.1
Name: goat-sdk-wallet-multiversx
Version: 0.1.0
Summary: Goat SDK MultiversX wallet implementation
Home-page: https://ohmygoat.dev/
Keywords: goat,sdk,multiversx,agents,ai,wallet
Author: Ofem Eteng
Author-email: ofemeteng@gmail.com
Requires-Python: >=3.10,<4.0
Classifier: Programming Language :: Python :: 3
Classifier: Programming Language :: Python :: 3.10
Classifier: Programming Language :: Python :: 3.11
Classifier: Programming Language :: Python :: 3.12
Requires-Dist: goat-sdk (>=0.1.0,<0.2.0)
Requires-Dist: multiversx-sdk (>=1.1.1)
Requires-Dist: pydantic (>=2.0.0,<3.0.0)
Project-URL: Bug Tracker, https://github.com/goat-sdk/goat/issues
Project-URL: Repository, https://github.com/goat-sdk/goat
